setup.py
twsfolders/__init__.py
twsfolders/_compat.py
twsfolders/_logger.py
twsfolders/folder.py
twsfolders/interface.py
twsfolders/item.py
twsfolders/prefixes.py
twsfolders/rootfolders.py
twsfolders.egg-info/PKG-INFO
twsfolders.egg-info/SOURCES.txt
twsfolders.egg-info/dependency_links.txt
twsfolders.egg-info/requires.txt
twsfolders.egg-info/top_level.txt
twsfolders.egg-info/zip-safe
twsfolders/tests/__init__.py
twsfolders/tests/application.py
twsfolders/tests/test_folder.py
twsfolders/tests/test_rootfolders.py