Metadata-Version: 1.1
Name: twsfolders
Version: 0.1.0
Summary: TeamWorks Folders
Home-page: https://github.com/ldjebran/twsfolders
Author: Djebran Lezzoum
Author-email: ldjebran@gmail.com
License: Apache 2.0
Keywords: ZODDB persistent folders folder item url rootfolders
Platform: any
Classifier: Programming Language :: Python :: 2.7
